merge_segments/__init__.py
merge_segments/merge.py
merge_segments-0.6.1.dist-info/METADATA
merge_segments-0.6.1.dist-info/WHEEL
merge_segments-0.6.1.dist-info/RECORD
