Metadata-Version: 2.1
Name: merge_segments
Version: 0.6.1
Summary: A tool for merging data onto a road network segmentation
Project-URL: Homepage, https://github.com/thehappycheese/merge-segments
Author: Nicholas Archer
Classifier: Development Status :: 5 - Production/Stable
Classifier: Programming Language :: Python :: 3.8
Classifier: Programming Language :: Python :: 3.9
Classifier: Programming Language :: Python :: 3.10
Requires-Python: >=3.8
Requires-Dist: deprecated>=1.2
Requires-Dist: pandas>=1.2.3
Requires-Dist: requests>=2.25
